nicegui_calculator/__init__.py
nicegui_calculator/__main__.py
nicegui_calculator/calculator.py
nicegui_calculator/main.py
nicegui_calculator/py.typed
nicegui_calculator-0.1.4.dist-info/METADATA
nicegui_calculator-0.1.4.dist-info/WHEEL
nicegui_calculator-0.1.4.dist-info/entry_points.txt
nicegui_calculator-0.1.4.dist-info/licenses/LICENSE
nicegui_calculator-0.1.4.dist-info/RECORD
